sms_messenger/__init__.py
sms_messenger-1.2.0.dist-info/LICENSE
sms_messenger-1.2.0.dist-info/METADATA
sms_messenger-1.2.0.dist-info/WHEEL
sms_messenger-1.2.0.dist-info/top_level.txt
sms_messenger-1.2.0.dist-info/RECORD
