Metadata-Version: 2.1
Name: sms-messenger
Version: 1.2.0
Summary: A simple Python package for sending messages over SMS Gateways.
Home-page: https://github.com/coolspykee/sms_messenger
Author: Kenan Turner
Author-email: coolspykee@satx.rr.com
License: MIT
Platform: UNKNOWN
Classifier: Programming Language :: Python :: 3
Classifier: License :: OSI Approved :: MIT License
Classifier: Operating System :: OS Independent
Requires-Python: >=3.6
Requires-Dist: imapclient (>=2.1.0)
Requires-Dist: pyzmail (>=1.0.3)
